[
    {
        "id": "SYS_20260203082156742708",
        "timestamp": "03/02/2026 08:21:56",
        "timestamp_iso": "2026-02-03T08:21:56.742723",
        "action": "Cardápio Atualizado",
        "user": "Sistema",
        "category": "Cardápio",
        "details": {
            "id": "101",
            "name": "Medalhão com risotto de champignon e molho especial (Individual)",
            "category": "Pratos",
            "message": "Produto \"Medalhão com risotto de champignon e molho especial (Individual)\" atualizado."
        }
    },
    {
        "id": "SYS_20260203082245764062",
        "timestamp": "03/02/2026 08:22:45",
        "timestamp_iso": "2026-02-03T08:22:45.764082",
        "action": "Cardápio Atualizado",
        "user": "Sistema",
        "category": "Cardápio",
        "details": {
            "id": "101",
            "name": "Medalhão com risotto de champignon e molho especial (Individual)",
            "category": "Pratos",
            "message": "Produto \"Medalhão com risotto de champignon e molho especial (Individual)\" atualizado."
        }
    },
    {
        "id": "SYS_20260203082557351289",
        "timestamp": "03/02/2026 08:25:57",
        "timestamp_iso": "2026-02-03T08:25:57.351307",
        "action": "Cardápio Atualizado",
        "user": "Sistema",
        "category": "Cardápio",
        "details": {
            "id": "101",
            "name": "Medalhão com risotto de champignon e molho especial (Individual)",
            "category": "Pratos",
            "message": "Produto \"Medalhão com risotto de champignon e molho especial (Individual)\" atualizado."
        }
    },
    {
        "id": "SYS_20260203101550322083",
        "timestamp": "03/02/2026 10:15:50",
        "timestamp_iso": "2026-02-03T10:15:50.322116",
        "action": "Login Falhou",
        "user": "admin",
        "category": "Autenticação",
        "details": "Tentativa de usuário inexistente: admin"
    },
    {
        "id": "SYS_20260203101742381946",
        "timestamp": "03/02/2026 10:17:42",
        "timestamp_iso": "2026-02-03T10:17:42.381964",
        "action": "Login Falhou",
        "user": "admin",
        "category": "Autenticação",
        "details": "Tentativa de usuário inexistente: admin"
    },
    {
        "id": "SYS_20260203101935675896",
        "timestamp": "03/02/2026 10:19:35",
        "timestamp_iso": "2026-02-03T10:19:35.675913",
        "action": "Login Falhou",
        "user": "admin",
        "category": "Autenticação",
        "details": "Tentativa de usuário inexistente: admin"
    },
    {
        "id": "SYS_20260203102100099286",
        "timestamp": "03/02/2026 10:21:00",
        "timestamp_iso": "2026-02-03T10:21:00.099306",
        "action": "Login",
        "user": "Angelo",
        "category": "Autenticação",
        "details": "Usuário Angelo entrou no sistema"
    },
    {
        "id": "SYS_20260203102104227433",
        "timestamp": "03/02/2026 10:21:04",
        "timestamp_iso": "2026-02-03T10:21:04.227448",
        "action": "Cardápio Criado",
        "user": "Sistema",
        "category": "Cardápio",
        "details": {
            "name": "Produto Teste Debug",
            "category": "Testes",
            "message": "Produto \"Produto Teste Debug\" criado."
        }
    },
    {
        "id": "SYS_20260203102424176531",
        "timestamp": "03/02/2026 10:24:24",
        "timestamp_iso": "2026-02-03T10:24:24.176549",
        "action": "Login",
        "user": "Angelo",
        "category": "Autenticação",
        "details": "Usuário Angelo entrou no sistema"
    },
    {
        "id": "SYS_20260203102428262005",
        "timestamp": "03/02/2026 10:24:28",
        "timestamp_iso": "2026-02-03T10:24:28.262020",
        "action": "Cardápio Atualizado",
        "user": "Sistema",
        "category": "Cardápio",
        "details": {
            "id": "2",
            "name": "Acai Updated",
            "category": "Sobremesas",
            "message": "Produto \"Acai Updated\" atualizado."
        }
    },
    {
        "id": "SYS_20260203102545778613",
        "timestamp": "03/02/2026 10:25:45",
        "timestamp_iso": "2026-02-03T10:25:45.778631",
        "action": "Login",
        "user": "Angelo",
        "category": "Autenticação",
        "details": "Usuário Angelo entrou no sistema"
    },
    {
        "id": "SYS_20260203102549862305",
        "timestamp": "03/02/2026 10:25:49",
        "timestamp_iso": "2026-02-03T10:25:49.862318",
        "action": "Cardápio Atualizado",
        "user": "Sistema",
        "category": "Cardápio",
        "details": {
            "id": "2",
            "name": "Acai Updated Disabled",
            "category": "Sobremesas",
            "message": "Produto \"Acai Updated Disabled\" atualizado."
        }
    },
    {
        "id": "SYS_20260203134135141940",
        "timestamp": "03/02/2026 13:41:35",
        "timestamp_iso": "2026-02-03T13:41:35.141957",
        "action": "Cardápio Atualizado",
        "user": "Sistema",
        "category": "Cardápio",
        "details": {
            "id": "101",
            "name": "Medalhão com risotto de champignon e molho especial (Individual)",
            "category": "Pratos",
            "message": "Produto \"Medalhão com risotto de champignon e molho especial (Individual)\" atualizado."
        }
    },
    {
        "id": "SYS_20260203135759178051",
        "timestamp": "03/02/2026 13:57:59",
        "timestamp_iso": "2026-02-03T13:57:59.178067",
        "action": "Cardápio Criado",
        "user": "Sistema",
        "category": "Cardápio",
        "details": {
            "name": "Bolo Especial",
            "category": "Sobremesas",
            "message": "Produto \"Bolo Especial\" criado."
        }
    },
    {
        "id": "SYS_20260203135759244440",
        "timestamp": "03/02/2026 13:57:59",
        "timestamp_iso": "2026-02-03T13:57:59.244453",
        "action": "Cardápio Atualizado",
        "user": "Sistema",
        "category": "Cardápio",
        "details": {
            "id": "1",
            "name": "Bolo Especial (Editado)",
            "category": "Sobremesas",
            "message": "Produto \"Bolo Especial (Editado)\" atualizado."
        }
    },
    {
        "id": "SYS_20260203152058410659",
        "timestamp": "03/02/2026 15:20:58",
        "timestamp_iso": "2026-02-03T15:20:58.410683",
        "action": "cancel_consumption",
        "user": "admin_user",
        "category": "Cancelamento",
        "details": {
            "charge_id": "CHARGE_TEST_001",
            "room_number": "101",
            "total": 100.0,
            "old_status": "pending",
            "justification": "Erro de lançamento"
        }
    },
    {
        "id": "SYS_20260203152059229483",
        "timestamp": "03/02/2026 15:20:59",
        "timestamp_iso": "2026-02-03T15:20:59.229500",
        "action": "cancel_consumption",
        "user": "admin_user",
        "category": "Cancelamento",
        "details": {
            "charge_id": "TEST_CHARGE_20260203152059",
            "room_number": "999",
            "total": 10.0,
            "old_status": "pending",
            "justification": "Integration Test Justification"
        }
    },
    {
        "id": "SYS_20260203152059327112",
        "timestamp": "03/02/2026 15:20:59",
        "timestamp_iso": "2026-02-03T15:20:59.327126",
        "action": "Cardápio Criado",
        "user": "Sistema",
        "category": "Cardápio",
        "details": {
            "name": "Test Burger",
            "category": "Lanches",
            "message": "Produto \"Test Burger\" criado."
        }
    },
    {
        "id": "SYS_20260203152059670710",
        "timestamp": "03/02/2026 15:20:59",
        "timestamp_iso": "2026-02-03T15:20:59.670722",
        "action": "transfer_item",
        "user": "SupervisorUser",
        "category": "Restaurante",
        "details": {
            "description": "Transferiu 1.0x Coke da Mesa 10 para Mesa 20",
            "source_table": "10",
            "target_table": "20",
            "item": "Coke",
            "qty": 1.0,
            "user": "SupervisorUser"
        }
    },
    {
        "id": "SYS_20260203152059682759",
        "timestamp": "03/02/2026 15:20:59",
        "timestamp_iso": "2026-02-03T15:20:59.682771",
        "action": "transfer_item",
        "user": "SupervisorUser",
        "category": "Restaurante",
        "details": {
            "description": "Transferiu 1.0x Coke da Mesa 10 para Mesa 20",
            "source_table": "10",
            "target_table": "20",
            "item": "Coke",
            "qty": 1.0,
            "user": "SupervisorUser"
        }
    },
    {
        "id": "SYS_20260203152059696361",
        "timestamp": "03/02/2026 15:20:59",
        "timestamp_iso": "2026-02-03T15:20:59.696374",
        "action": "transfer_to_room",
        "user": "Admin",
        "category": "Geral",
        "details": {
            "source_table": "10",
            "target_room": "101",
            "total": 22.0,
            "items": [
                {
                    "name": "Burger",
                    "price": 20,
                    "qty": 1,
                    "source": "restaurant"
                }
            ],
            "user": "Admin",
            "description": "Mesa 10 -> Quarto 101"
        }
    },
    {
        "id": "SYS_20260203152059708950",
        "timestamp": "03/02/2026 15:20:59",
        "timestamp_iso": "2026-02-03T15:20:59.708966",
        "action": "transfer_to_room",
        "user": "Admin",
        "category": "Geral",
        "details": {
            "source_table": "10",
            "target_room": "101",
            "total": 22.0,
            "items": [
                {
                    "name": "Burger",
                    "price": 20,
                    "qty": 1,
                    "source": "restaurant"
                }
            ],
            "user": "Admin",
            "description": "Mesa 10 -> Quarto 101"
        }
    },
    {
        "id": "SYS_20260203152059721855",
        "timestamp": "03/02/2026 15:20:59",
        "timestamp_iso": "2026-02-03T15:20:59.721869",
        "action": "transfer_to_room",
        "user": "Admin",
        "category": "Geral",
        "details": {
            "source_table": "10",
            "target_room": "101",
            "total": 22.0,
            "items": [
                {
                    "name": "Burger",
                    "price": 20,
                    "qty": 1,
                    "source": "restaurant"
                }
            ],
            "user": "Admin",
            "description": "Mesa 10 -> Quarto 101"
        }
    },
    {
        "id": "SYS_20260203152310144378",
        "timestamp": "03/02/2026 15:23:10",
        "timestamp_iso": "2026-02-03T15:23:10.144389",
        "action": "close_cashier",
        "user": "test_user",
        "category": "Caixa",
        "details": {
            "session_id": "SESSION_123",
            "closing_balance": 100.0,
            "difference": 0.0,
            "opened_at": "01/01/2026 10:00",
            "closed_at": "03/02/2026 15:23",
            "department": "Recepção"
        }
    },
    {
        "id": "SYS_20260203152321274840",
        "timestamp": "03/02/2026 15:23:21",
        "timestamp_iso": "2026-02-03T15:23:21.274853",
        "action": "close_cashier",
        "user": "test_user",
        "category": "Caixa",
        "details": {
            "session_id": "SESSION_123",
            "closing_balance": 100.0,
            "difference": 0.0,
            "opened_at": "01/01/2026 10:00",
            "closed_at": "03/02/2026 15:23",
            "department": "Recepção"
        }
    },
    {
        "id": "SYS_20260203153127005682",
        "timestamp": "03/02/2026 15:31:27",
        "timestamp_iso": "2026-02-03T15:31:27.005695",
        "action": "close_cashier",
        "user": "test_user",
        "category": "Caixa",
        "details": {
            "session_id": "SESSION_123",
            "closing_balance": 100.0,
            "difference": 0.0,
            "opened_at": "01/01/2026 10:00",
            "closed_at": "03/02/2026 15:31",
            "department": "Recepção"
        }
    },
    {
        "id": "SYS_20260203153127149733",
        "timestamp": "03/02/2026 15:31:27",
        "timestamp_iso": "2026-02-03T15:31:27.149752",
        "action": "transfer_to_room",
        "user": "Admin",
        "category": "Geral",
        "details": {
            "source_table": "40",
            "target_room": "01",
            "total": 100.0,
            "items": [
                {
                    "name": "Item 1",
                    "price": 100.0,
                    "qty": 1,
                    "waiter": "Waiter1"
                }
            ],
            "user": "Admin",
            "description": "Mesa 40 -> Quarto 01"
        }
    },
    {
        "id": "SYS_20260203153127180718",
        "timestamp": "03/02/2026 15:31:27",
        "timestamp_iso": "2026-02-03T15:31:27.180734",
        "action": "transfer_to_room",
        "user": "Admin",
        "category": "Geral",
        "details": {
            "source_table": "41",
            "target_room": "01",
            "total": 110.0,
            "items": [
                {
                    "name": "Item 2",
                    "price": 100.0,
                    "qty": 1,
                    "waiter": "Waiter1"
                }
            ],
            "user": "Admin",
            "description": "Mesa 41 -> Quarto 01"
        }
    },
    {
        "id": "SYS_20260203153127208619",
        "timestamp": "03/02/2026 15:31:27",
        "timestamp_iso": "2026-02-03T15:31:27.208636",
        "action": "cancel_consumption",
        "user": "admin_user",
        "category": "Cancelamento",
        "details": {
            "charge_id": "CHARGE_TEST_001",
            "room_number": "101",
            "total": 100.0,
            "old_status": "pending",
            "justification": "Erro de lançamento"
        }
    },
    {
        "id": "SYS_20260203153128188320",
        "timestamp": "03/02/2026 15:31:28",
        "timestamp_iso": "2026-02-03T15:31:28.188337",
        "action": "transfer_to_room",
        "user": "admin",
        "category": "Geral",
        "details": {
            "source_table": "33",
            "target_room": "33",
            "total": 5.5,
            "items": [
                {
                    "id": "912ae08d-5492-41e5-805a-d16e077f12c6",
                    "printed": false,
                    "print_status": "error",
                    "name": "Coca Cola",
                    "flavor": null,
                    "qty": 1.0,
                    "price": 5.0,
                    "complements": [],
                    "accompaniments": [],
                    "questions_answers": [],
                    "observations": [],
                    "category": "Bebidas",
                    "service_fee_exempt": false,
                    "source": "restaurant",
                    "waiter": "GarcomZ",
                    "created_at": "03/02/2026 15:31"
                }
            ],
            "user": "admin",
            "description": "Mesa 33 -> Quarto 33"
        }
    },
    {
        "id": "SYS_20260203153129047846",
        "timestamp": "03/02/2026 15:31:29",
        "timestamp_iso": "2026-02-03T15:31:29.047862",
        "action": "cancel_consumption",
        "user": "admin_user",
        "category": "Cancelamento",
        "details": {
            "charge_id": "TEST_CHARGE_20260203153129",
            "room_number": "999",
            "total": 10.0,
            "old_status": "pending",
            "justification": "Integration Test Justification"
        }
    },
    {
        "id": "SYS_20260203153129217212",
        "timestamp": "03/02/2026 15:31:29",
        "timestamp_iso": "2026-02-03T15:31:29.217228",
        "action": "Cardápio Criado",
        "user": "Sistema",
        "category": "Cardápio",
        "details": {
            "name": "Test Burger",
            "category": "Lanches",
            "message": "Produto \"Test Burger\" criado."
        }
    },
    {
        "id": "SYS_20260203153129399158",
        "timestamp": "03/02/2026 15:31:29",
        "timestamp_iso": "2026-02-03T15:31:29.399179",
        "action": "Cardápio Criado",
        "user": "Sistema",
        "category": "Cardápio",
        "details": {
            "name": "Bolo Especial",
            "category": "Sobremesas",
            "message": "Produto \"Bolo Especial\" criado."
        }
    },
    {
        "id": "SYS_20260203153129442016",
        "timestamp": "03/02/2026 15:31:29",
        "timestamp_iso": "2026-02-03T15:31:29.442031",
        "action": "Cardápio Atualizado",
        "user": "Sistema",
        "category": "Cardápio",
        "details": {
            "id": "1",
            "name": "Bolo Especial (Editado)",
            "category": "Sobremesas",
            "message": "Produto \"Bolo Especial (Editado)\" atualizado."
        }
    },
    {
        "id": "SYS_20260203153129714201",
        "timestamp": "03/02/2026 15:31:29",
        "timestamp_iso": "2026-02-03T15:31:29.714217",
        "action": "transfer_item",
        "user": "SupervisorUser",
        "category": "Restaurante",
        "details": {
            "description": "Transferiu 1.0x Coke da Mesa 10 para Mesa 20",
            "source_table": "10",
            "target_table": "20",
            "item": "Coke",
            "qty": 1.0,
            "user": "SupervisorUser"
        }
    },
    {
        "id": "SYS_20260203153129728398",
        "timestamp": "03/02/2026 15:31:29",
        "timestamp_iso": "2026-02-03T15:31:29.728411",
        "action": "transfer_item",
        "user": "SupervisorUser",
        "category": "Restaurante",
        "details": {
            "description": "Transferiu 1.0x Coke da Mesa 10 para Mesa 20",
            "source_table": "10",
            "target_table": "20",
            "item": "Coke",
            "qty": 1.0,
            "user": "SupervisorUser"
        }
    },
    {
        "id": "SYS_20260203153129752843",
        "timestamp": "03/02/2026 15:31:29",
        "timestamp_iso": "2026-02-03T15:31:29.752860",
        "action": "transfer_to_room",
        "user": "Admin",
        "category": "Geral",
        "details": {
            "source_table": "10",
            "target_room": "101",
            "total": 22.0,
            "items": [
                {
                    "name": "Burger",
                    "price": 20,
                    "qty": 1,
                    "source": "restaurant"
                }
            ],
            "user": "Admin",
            "description": "Mesa 10 -> Quarto 101"
        }
    },
    {
        "id": "SYS_20260203153129765830",
        "timestamp": "03/02/2026 15:31:29",
        "timestamp_iso": "2026-02-03T15:31:29.765850",
        "action": "transfer_to_room",
        "user": "Admin",
        "category": "Geral",
        "details": {
            "source_table": "10",
            "target_room": "101",
            "total": 22.0,
            "items": [
                {
                    "name": "Burger",
                    "price": 20,
                    "qty": 1,
                    "source": "restaurant"
                }
            ],
            "user": "Admin",
            "description": "Mesa 10 -> Quarto 101"
        }
    },
    {
        "id": "SYS_20260203153129782684",
        "timestamp": "03/02/2026 15:31:29",
        "timestamp_iso": "2026-02-03T15:31:29.782699",
        "action": "transfer_to_room",
        "user": "Admin",
        "category": "Geral",
        "details": {
            "source_table": "10",
            "target_room": "101",
            "total": 22.0,
            "items": [
                {
                    "name": "Burger",
                    "price": 20,
                    "qty": 1,
                    "source": "restaurant"
                }
            ],
            "user": "Admin",
            "description": "Mesa 10 -> Quarto 101"
        }
    },
    {
        "id": "SYS_20260203153129825078",
        "timestamp": "03/02/2026 15:31:29",
        "timestamp_iso": "2026-02-03T15:31:29.825094",
        "action": "transfer_to_room",
        "user": "Admin",
        "category": "Geral",
        "details": {
            "source_table": "50",
            "target_room": "10",
            "total": 77.0,
            "items": [
                {
                    "id": "item1",
                    "name": "Burger",
                    "qty": 1,
                    "price": 50.0,
                    "waiter": "Waiter A"
                },
                {
                    "id": "item2",
                    "name": "Coke",
                    "qty": 2,
                    "price": 10.0,
                    "waiter": "Waiter B"
                }
            ],
            "user": "Admin",
            "description": "Mesa 50 -> Quarto 10"
        }
    },
    {
        "id": "SYS_20260203153553830503",
        "timestamp": "03/02/2026 15:35:53",
        "timestamp_iso": "2026-02-03T15:35:53.830515",
        "action": "close_cashier",
        "user": "test_user",
        "category": "Caixa",
        "details": {
            "session_id": "SESSION_123",
            "closing_balance": 100.0,
            "difference": 0.0,
            "opened_at": "01/01/2026 10:00",
            "closed_at": "03/02/2026 15:35",
            "department": "Recepção"
        }
    },
    {
        "id": "SYS_20260203153554002623",
        "timestamp": "03/02/2026 15:35:54",
        "timestamp_iso": "2026-02-03T15:35:54.002642",
        "action": "transfer_to_room",
        "user": "Admin",
        "category": "Geral",
        "details": {
            "source_table": "40",
            "target_room": "01",
            "total": 100.0,
            "items": [
                {
                    "name": "Item 1",
                    "price": 100.0,
                    "qty": 1,
                    "waiter": "Waiter1"
                }
            ],
            "user": "Admin",
            "description": "Mesa 40 -> Quarto 01"
        }
    },
    {
        "id": "SYS_20260203153554032933",
        "timestamp": "03/02/2026 15:35:54",
        "timestamp_iso": "2026-02-03T15:35:54.032949",
        "action": "transfer_to_room",
        "user": "Admin",
        "category": "Geral",
        "details": {
            "source_table": "41",
            "target_room": "01",
            "total": 110.0,
            "items": [
                {
                    "name": "Item 2",
                    "price": 100.0,
                    "qty": 1,
                    "waiter": "Waiter1"
                }
            ],
            "user": "Admin",
            "description": "Mesa 41 -> Quarto 01"
        }
    },
    {
        "id": "SYS_20260203153554062976",
        "timestamp": "03/02/2026 15:35:54",
        "timestamp_iso": "2026-02-03T15:35:54.062989",
        "action": "cancel_consumption",
        "user": "admin_user",
        "category": "Cancelamento",
        "details": {
            "charge_id": "CHARGE_TEST_001",
            "room_number": "101",
            "total": 100.0,
            "old_status": "pending",
            "justification": "Erro de lançamento"
        }
    },
    {
        "id": "SYS_20260203153555110199",
        "timestamp": "03/02/2026 15:35:55",
        "timestamp_iso": "2026-02-03T15:35:55.110212",
        "action": "transfer_to_room",
        "user": "admin",
        "category": "Geral",
        "details": {
            "source_table": "33",
            "target_room": "33",
            "total": 5.5,
            "items": [
                {
                    "id": "bd13e4ed-a5a6-4d76-be9f-7c232d3219c7",
                    "printed": false,
                    "print_status": "error",
                    "name": "Coca Cola",
                    "flavor": null,
                    "qty": 1.0,
                    "price": 5.0,
                    "complements": [],
                    "accompaniments": [],
                    "questions_answers": [],
                    "observations": [],
                    "category": "Bebidas",
                    "service_fee_exempt": false,
                    "source": "restaurant",
                    "waiter": "GarcomZ",
                    "created_at": "03/02/2026 15:35"
                }
            ],
            "user": "admin",
            "description": "Mesa 33 -> Quarto 33"
        }
    },
    {
        "id": "SYS_20260203153556156002",
        "timestamp": "03/02/2026 15:35:56",
        "timestamp_iso": "2026-02-03T15:35:56.156018",
        "action": "cancel_consumption",
        "user": "admin_user",
        "category": "Cancelamento",
        "details": {
            "charge_id": "TEST_CHARGE_20260203153556",
            "room_number": "999",
            "total": 10.0,
            "old_status": "pending",
            "justification": "Integration Test Justification"
        }
    },
    {
        "id": "SYS_20260203153556340794",
        "timestamp": "03/02/2026 15:35:56",
        "timestamp_iso": "2026-02-03T15:35:56.340809",
        "action": "Cardápio Criado",
        "user": "Sistema",
        "category": "Cardápio",
        "details": {
            "name": "Test Burger",
            "category": "Lanches",
            "message": "Produto \"Test Burger\" criado."
        }
    },
    {
        "id": "SYS_20260203153556562680",
        "timestamp": "03/02/2026 15:35:56",
        "timestamp_iso": "2026-02-03T15:35:56.562695",
        "action": "Cardápio Criado",
        "user": "Sistema",
        "category": "Cardápio",
        "details": {
            "name": "Bolo Especial",
            "category": "Sobremesas",
            "message": "Produto \"Bolo Especial\" criado."
        }
    },
    {
        "id": "SYS_20260203153556608838",
        "timestamp": "03/02/2026 15:35:56",
        "timestamp_iso": "2026-02-03T15:35:56.608853",
        "action": "Cardápio Atualizado",
        "user": "Sistema",
        "category": "Cardápio",
        "details": {
            "id": "1",
            "name": "Bolo Especial (Editado)",
            "category": "Sobremesas",
            "message": "Produto \"Bolo Especial (Editado)\" atualizado."
        }
    },
    {
        "id": "SYS_20260203153556857406",
        "timestamp": "03/02/2026 15:35:56",
        "timestamp_iso": "2026-02-03T15:35:56.857423",
        "action": "transfer_item",
        "user": "SupervisorUser",
        "category": "Restaurante",
        "details": {
            "description": "Transferiu 1.0x Coke da Mesa 10 para Mesa 20",
            "source_table": "10",
            "target_table": "20",
            "item": "Coke",
            "qty": 1.0,
            "user": "SupervisorUser"
        }
    },
    {
        "id": "SYS_20260203153556873764",
        "timestamp": "03/02/2026 15:35:56",
        "timestamp_iso": "2026-02-03T15:35:56.873776",
        "action": "transfer_item",
        "user": "SupervisorUser",
        "category": "Restaurante",
        "details": {
            "description": "Transferiu 1.0x Coke da Mesa 10 para Mesa 20",
            "source_table": "10",
            "target_table": "20",
            "item": "Coke",
            "qty": 1.0,
            "user": "SupervisorUser"
        }
    },
    {
        "id": "SYS_20260203153556899448",
        "timestamp": "03/02/2026 15:35:56",
        "timestamp_iso": "2026-02-03T15:35:56.899464",
        "action": "transfer_to_room",
        "user": "Admin",
        "category": "Geral",
        "details": {
            "source_table": "10",
            "target_room": "101",
            "total": 22.0,
            "items": [
                {
                    "name": "Burger",
                    "price": 20,
                    "qty": 1,
                    "source": "restaurant"
                }
            ],
            "user": "Admin",
            "description": "Mesa 10 -> Quarto 101"
        }
    },
    {
        "id": "SYS_20260203153556912254",
        "timestamp": "03/02/2026 15:35:56",
        "timestamp_iso": "2026-02-03T15:35:56.912268",
        "action": "transfer_to_room",
        "user": "Admin",
        "category": "Geral",
        "details": {
            "source_table": "10",
            "target_room": "101",
            "total": 22.0,
            "items": [
                {
                    "name": "Burger",
                    "price": 20,
                    "qty": 1,
                    "source": "restaurant"
                }
            ],
            "user": "Admin",
            "description": "Mesa 10 -> Quarto 101"
        }
    },
    {
        "id": "SYS_20260203153556930027",
        "timestamp": "03/02/2026 15:35:56",
        "timestamp_iso": "2026-02-03T15:35:56.930046",
        "action": "transfer_to_room",
        "user": "Admin",
        "category": "Geral",
        "details": {
            "source_table": "10",
            "target_room": "101",
            "total": 22.0,
            "items": [
                {
                    "name": "Burger",
                    "price": 20,
                    "qty": 1,
                    "source": "restaurant"
                }
            ],
            "user": "Admin",
            "description": "Mesa 10 -> Quarto 101"
        }
    },
    {
        "id": "SYS_20260203153556960575",
        "timestamp": "03/02/2026 15:35:56",
        "timestamp_iso": "2026-02-03T15:35:56.960591",
        "action": "transfer_to_room",
        "user": "Admin",
        "category": "Geral",
        "details": {
            "source_table": "50",
            "target_room": "10",
            "total": 77.0,
            "items": [
                {
                    "id": "item1",
                    "name": "Burger",
                    "qty": 1,
                    "price": 50.0,
                    "waiter": "Waiter A"
                },
                {
                    "id": "item2",
                    "name": "Coke",
                    "qty": 2,
                    "price": 10.0,
                    "waiter": "Waiter B"
                }
            ],
            "user": "Admin",
            "description": "Mesa 50 -> Quarto 10"
        }
    },
    {
        "id": "SYS_20260203154821085140",
        "timestamp": "03/02/2026 15:48:21",
        "timestamp_iso": "2026-02-03T15:48:21.085151",
        "action": "close_cashier",
        "user": "test_user",
        "category": "Caixa",
        "details": {
            "session_id": "SESSION_123",
            "closing_balance": 100.0,
            "difference": 0.0,
            "opened_at": "01/01/2026 10:00",
            "closed_at": "03/02/2026 15:48",
            "department": "Recepção"
        }
    },
    {
        "id": "SYS_20260203154821218155",
        "timestamp": "03/02/2026 15:48:21",
        "timestamp_iso": "2026-02-03T15:48:21.218173",
        "action": "transfer_to_room",
        "user": "Admin",
        "category": "Geral",
        "details": {
            "source_table": "40",
            "target_room": "01",
            "total": 100.0,
            "items": [
                {
                    "name": "Item 1",
                    "price": 100.0,
                    "qty": 1,
                    "waiter": "Waiter1"
                }
            ],
            "user": "Admin",
            "description": "Mesa 40 -> Quarto 01"
        }
    },
    {
        "id": "SYS_20260203154821249437",
        "timestamp": "03/02/2026 15:48:21",
        "timestamp_iso": "2026-02-03T15:48:21.249453",
        "action": "transfer_to_room",
        "user": "Admin",
        "category": "Geral",
        "details": {
            "source_table": "41",
            "target_room": "01",
            "total": 110.0,
            "items": [
                {
                    "name": "Item 2",
                    "price": 100.0,
                    "qty": 1,
                    "waiter": "Waiter1"
                }
            ],
            "user": "Admin",
            "description": "Mesa 41 -> Quarto 01"
        }
    },
    {
        "id": "SYS_20260203154821276449",
        "timestamp": "03/02/2026 15:48:21",
        "timestamp_iso": "2026-02-03T15:48:21.276463",
        "action": "cancel_consumption",
        "user": "admin_user",
        "category": "Cancelamento",
        "details": {
            "charge_id": "CHARGE_TEST_001",
            "room_number": "101",
            "total": 100.0,
            "old_status": "pending",
            "justification": "Erro de lançamento"
        }
    },
    {
        "id": "SYS_20260203154822126239",
        "timestamp": "03/02/2026 15:48:22",
        "timestamp_iso": "2026-02-03T15:48:22.126254",
        "action": "transfer_to_room",
        "user": "admin",
        "category": "Geral",
        "details": {
            "source_table": "33",
            "target_room": "33",
            "total": 5.5,
            "items": [
                {
                    "id": "69455bc1-fa79-463e-971a-9d466d1e2506",
                    "printed": false,
                    "print_status": "error",
                    "name": "Coca Cola",
                    "flavor": null,
                    "qty": 1.0,
                    "price": 5.0,
                    "complements": [],
                    "accompaniments": [],
                    "questions_answers": [],
                    "observations": [],
                    "category": "Bebidas",
                    "service_fee_exempt": false,
                    "source": "restaurant",
                    "waiter": "GarcomZ",
                    "created_at": "03/02/2026 15:48"
                }
            ],
            "user": "admin",
            "description": "Mesa 33 -> Quarto 33"
        }
    },
    {
        "id": "SYS_20260203154822583564",
        "timestamp": "03/02/2026 15:48:22",
        "timestamp_iso": "2026-02-03T15:48:22.583582",
        "action": "Login",
        "user": "admin",
        "category": "Autenticação",
        "details": "Usuário admin entrou no sistema"
    },
    {
        "id": "SYS_20260203154822873466",
        "timestamp": "03/02/2026 15:48:22",
        "timestamp_iso": "2026-02-03T15:48:22.873483",
        "action": "cancel_consumption",
        "user": "admin_user",
        "category": "Cancelamento",
        "details": {
            "charge_id": "TEST_CHARGE_20260203154822",
            "room_number": "999",
            "total": 10.0,
            "old_status": "pending",
            "justification": "Integration Test Justification"
        }
    },
    {
        "id": "SYS_20260203154823054759",
        "timestamp": "03/02/2026 15:48:23",
        "timestamp_iso": "2026-02-03T15:48:23.054772",
        "action": "Cardápio Criado",
        "user": "Sistema",
        "category": "Cardápio",
        "details": {
            "name": "Test Burger",
            "category": "Lanches",
            "message": "Produto \"Test Burger\" criado."
        }
    },
    {
        "id": "SYS_20260203154823396287",
        "timestamp": "03/02/2026 15:48:23",
        "timestamp_iso": "2026-02-03T15:48:23.396303",
        "action": "Cardápio Criado",
        "user": "Sistema",
        "category": "Cardápio",
        "details": {
            "name": "Bolo Especial",
            "category": "Sobremesas",
            "message": "Produto \"Bolo Especial\" criado."
        }
    },
    {
        "id": "SYS_20260203154823449096",
        "timestamp": "03/02/2026 15:48:23",
        "timestamp_iso": "2026-02-03T15:48:23.449108",
        "action": "Cardápio Atualizado",
        "user": "Sistema",
        "category": "Cardápio",
        "details": {
            "id": "1",
            "name": "Bolo Especial (Editado)",
            "category": "Sobremesas",
            "message": "Produto \"Bolo Especial (Editado)\" atualizado."
        }
    },
    {
        "id": "SYS_20260203154823709855",
        "timestamp": "03/02/2026 15:48:23",
        "timestamp_iso": "2026-02-03T15:48:23.709868",
        "action": "transfer_item",
        "user": "SupervisorUser",
        "category": "Restaurante",
        "details": {
            "description": "Transferiu 1.0x Coke da Mesa 10 para Mesa 20",
            "source_table": "10",
            "target_table": "20",
            "item": "Coke",
            "qty": 1.0,
            "user": "SupervisorUser"
        }
    },
    {
        "id": "SYS_20260203154823724861",
        "timestamp": "03/02/2026 15:48:23",
        "timestamp_iso": "2026-02-03T15:48:23.724871",
        "action": "transfer_item",
        "user": "SupervisorUser",
        "category": "Restaurante",
        "details": {
            "description": "Transferiu 1.0x Coke da Mesa 10 para Mesa 20",
            "source_table": "10",
            "target_table": "20",
            "item": "Coke",
            "qty": 1.0,
            "user": "SupervisorUser"
        }
    },
    {
        "id": "SYS_20260203154823749165",
        "timestamp": "03/02/2026 15:48:23",
        "timestamp_iso": "2026-02-03T15:48:23.749178",
        "action": "transfer_to_room",
        "user": "Admin",
        "category": "Geral",
        "details": {
            "source_table": "10",
            "target_room": "101",
            "total": 22.0,
            "items": [
                {
                    "name": "Burger",
                    "price": 20,
                    "qty": 1,
                    "source": "restaurant"
                }
            ],
            "user": "Admin",
            "description": "Mesa 10 -> Quarto 101"
        }
    },
    {
        "id": "SYS_20260203154823762319",
        "timestamp": "03/02/2026 15:48:23",
        "timestamp_iso": "2026-02-03T15:48:23.762332",
        "action": "transfer_to_room",
        "user": "Admin",
        "category": "Geral",
        "details": {
            "source_table": "10",
            "target_room": "101",
            "total": 22.0,
            "items": [
                {
                    "name": "Burger",
                    "price": 20,
                    "qty": 1,
                    "source": "restaurant"
                }
            ],
            "user": "Admin",
            "description": "Mesa 10 -> Quarto 101"
        }
    },
    {
        "id": "SYS_20260203154823778161",
        "timestamp": "03/02/2026 15:48:23",
        "timestamp_iso": "2026-02-03T15:48:23.778174",
        "action": "transfer_to_room",
        "user": "Admin",
        "category": "Geral",
        "details": {
            "source_table": "10",
            "target_room": "101",
            "total": 22.0,
            "items": [
                {
                    "name": "Burger",
                    "price": 20,
                    "qty": 1,
                    "source": "restaurant"
                }
            ],
            "user": "Admin",
            "description": "Mesa 10 -> Quarto 101"
        }
    },
    {
        "id": "SYS_20260203154823809262",
        "timestamp": "03/02/2026 15:48:23",
        "timestamp_iso": "2026-02-03T15:48:23.809276",
        "action": "transfer_to_room",
        "user": "Admin",
        "category": "Geral",
        "details": {
            "source_table": "50",
            "target_room": "10",
            "total": 77.0,
            "items": [
                {
                    "id": "item1",
                    "name": "Burger",
                    "qty": 1,
                    "price": 50.0,
                    "waiter": "Waiter A"
                },
                {
                    "id": "item2",
                    "name": "Coke",
                    "qty": 2,
                    "price": 10.0,
                    "waiter": "Waiter B"
                }
            ],
            "user": "Admin",
            "description": "Mesa 50 -> Quarto 10"
        }
    },
    {
        "id": "SYS_20260203155157978119",
        "timestamp": "03/02/2026 15:51:57",
        "timestamp_iso": "2026-02-03T15:51:57.978135",
        "action": "Login",
        "user": "admin",
        "category": "Autenticação",
        "details": "Usuário admin entrou no sistema"
    },
    {
        "id": "SYS_20260203164444951057",
        "timestamp": "03/02/2026 16:44:44",
        "timestamp_iso": "2026-02-03T16:44:44.951070",
        "action": "close_cashier",
        "user": "test_user",
        "category": "Caixa",
        "details": {
            "session_id": "SESSION_123",
            "closing_balance": 100.0,
            "difference": 0.0,
            "opened_at": "01/01/2026 10:00",
            "closed_at": "03/02/2026 16:44",
            "department": "Recepção"
        }
    },
    {
        "id": "SYS_20260203164445092936",
        "timestamp": "03/02/2026 16:44:45",
        "timestamp_iso": "2026-02-03T16:44:45.092953",
        "action": "transfer_to_room",
        "user": "Admin",
        "category": "Geral",
        "details": {
            "source_table": "40",
            "target_room": "01",
            "total": 100.0,
            "items": [
                {
                    "name": "Item 1",
                    "price": 100.0,
                    "qty": 1,
                    "waiter": "Waiter1"
                }
            ],
            "user": "Admin",
            "description": "Mesa 40 -> Quarto 01"
        }
    },
    {
        "id": "SYS_20260203164445123467",
        "timestamp": "03/02/2026 16:44:45",
        "timestamp_iso": "2026-02-03T16:44:45.123482",
        "action": "transfer_to_room",
        "user": "Admin",
        "category": "Geral",
        "details": {
            "source_table": "41",
            "target_room": "01",
            "total": 110.0,
            "items": [
                {
                    "name": "Item 2",
                    "price": 100.0,
                    "qty": 1,
                    "waiter": "Waiter1"
                }
            ],
            "user": "Admin",
            "description": "Mesa 41 -> Quarto 01"
        }
    },
    {
        "id": "SYS_20260203164445155039",
        "timestamp": "03/02/2026 16:44:45",
        "timestamp_iso": "2026-02-03T16:44:45.155053",
        "action": "cancel_consumption",
        "user": "admin_user",
        "category": "Cancelamento",
        "details": {
            "charge_id": "CHARGE_TEST_001",
            "room_number": "101",
            "total": 100.0,
            "old_status": "pending",
            "justification": "Erro de lançamento"
        }
    },
    {
        "id": "SYS_20260203164445905256",
        "timestamp": "03/02/2026 16:44:45",
        "timestamp_iso": "2026-02-03T16:44:45.905271",
        "action": "transfer_to_room",
        "user": "admin",
        "category": "Geral",
        "details": {
            "source_table": "33",
            "target_room": "33",
            "total": 5.5,
            "items": [
                {
                    "id": "8e318082-94b0-49bd-b104-28e5bf9b05e4",
                    "printed": false,
                    "print_status": "error",
                    "name": "Coca Cola",
                    "flavor": null,
                    "qty": 1.0,
                    "price": 5.0,
                    "complements": [],
                    "accompaniments": [],
                    "questions_answers": [],
                    "observations": [],
                    "category": "Bebidas",
                    "service_fee_exempt": false,
                    "source": "restaurant",
                    "waiter": "GarcomZ",
                    "created_at": "03/02/2026 16:44"
                }
            ],
            "user": "admin",
            "description": "Mesa 33 -> Quarto 33"
        }
    },
    {
        "id": "SYS_20260203164446380191",
        "timestamp": "03/02/2026 16:44:46",
        "timestamp_iso": "2026-02-03T16:44:46.380206",
        "action": "Login",
        "user": "admin",
        "category": "Autenticação",
        "details": "Usuário admin entrou no sistema"
    },
    {
        "id": "SYS_20260203164446914923",
        "timestamp": "03/02/2026 16:44:46",
        "timestamp_iso": "2026-02-03T16:44:46.914944",
        "action": "cancel_consumption",
        "user": "admin_user",
        "category": "Cancelamento",
        "details": {
            "charge_id": "TEST_CHARGE_20260203164446",
            "room_number": "999",
            "total": 10.0,
            "old_status": "pending",
            "justification": "Integration Test Justification"
        }
    },
    {
        "id": "SYS_20260203164447046187",
        "timestamp": "03/02/2026 16:44:47",
        "timestamp_iso": "2026-02-03T16:44:47.046201",
        "action": "Cardápio Criado",
        "user": "Sistema",
        "category": "Cardápio",
        "details": {
            "name": "Test Burger",
            "category": "Lanches",
            "message": "Produto \"Test Burger\" criado."
        }
    },
    {
        "id": "SYS_20260203164447447132",
        "timestamp": "03/02/2026 16:44:47",
        "timestamp_iso": "2026-02-03T16:44:47.447161",
        "action": "Cardápio Criado",
        "user": "Sistema",
        "category": "Cardápio",
        "details": {
            "name": "Bolo Especial",
            "category": "Sobremesas",
            "message": "Produto \"Bolo Especial\" criado."
        }
    },
    {
        "id": "SYS_20260203164447504641",
        "timestamp": "03/02/2026 16:44:47",
        "timestamp_iso": "2026-02-03T16:44:47.504656",
        "action": "Cardápio Atualizado",
        "user": "Sistema",
        "category": "Cardápio",
        "details": {
            "id": "1",
            "name": "Bolo Especial (Editado)",
            "category": "Sobremesas",
            "message": "Produto \"Bolo Especial (Editado)\" atualizado."
        }
    },
    {
        "id": "SYS_20260203164447757256",
        "timestamp": "03/02/2026 16:44:47",
        "timestamp_iso": "2026-02-03T16:44:47.757268",
        "action": "transfer_item",
        "user": "SupervisorUser",
        "category": "Restaurante",
        "details": {
            "description": "Transferiu 1.0x Coke da Mesa 10 para Mesa 20",
            "source_table": "10",
            "target_table": "20",
            "item": "Coke",
            "qty": 1.0,
            "user": "SupervisorUser"
        }
    },
    {
        "id": "SYS_20260203164447774386",
        "timestamp": "03/02/2026 16:44:47",
        "timestamp_iso": "2026-02-03T16:44:47.774400",
        "action": "transfer_item",
        "user": "SupervisorUser",
        "category": "Restaurante",
        "details": {
            "description": "Transferiu 1.0x Coke da Mesa 10 para Mesa 20",
            "source_table": "10",
            "target_table": "20",
            "item": "Coke",
            "qty": 1.0,
            "user": "SupervisorUser"
        }
    },
    {
        "id": "SYS_20260203164447802228",
        "timestamp": "03/02/2026 16:44:47",
        "timestamp_iso": "2026-02-03T16:44:47.802245",
        "action": "transfer_to_room",
        "user": "Admin",
        "category": "Geral",
        "details": {
            "source_table": "10",
            "target_room": "101",
            "total": 22.0,
            "items": [
                {
                    "name": "Burger",
                    "price": 20,
                    "qty": 1,
                    "source": "restaurant"
                }
            ],
            "user": "Admin",
            "description": "Mesa 10 -> Quarto 101"
        }
    },
    {
        "id": "SYS_20260203164447818513",
        "timestamp": "03/02/2026 16:44:47",
        "timestamp_iso": "2026-02-03T16:44:47.818529",
        "action": "transfer_to_room",
        "user": "Admin",
        "category": "Geral",
        "details": {
            "source_table": "10",
            "target_room": "101",
            "total": 22.0,
            "items": [
                {
                    "name": "Burger",
                    "price": 20,
                    "qty": 1,
                    "source": "restaurant"
                }
            ],
            "user": "Admin",
            "description": "Mesa 10 -> Quarto 101"
        }
    },
    {
        "id": "SYS_20260203164447838034",
        "timestamp": "03/02/2026 16:44:47",
        "timestamp_iso": "2026-02-03T16:44:47.838055",
        "action": "transfer_to_room",
        "user": "Admin",
        "category": "Geral",
        "details": {
            "source_table": "10",
            "target_room": "101",
            "total": 22.0,
            "items": [
                {
                    "name": "Burger",
                    "price": 20,
                    "qty": 1,
                    "source": "restaurant"
                }
            ],
            "user": "Admin",
            "description": "Mesa 10 -> Quarto 101"
        }
    },
    {
        "id": "SYS_20260203164447875954",
        "timestamp": "03/02/2026 16:44:47",
        "timestamp_iso": "2026-02-03T16:44:47.875971",
        "action": "transfer_to_room",
        "user": "Admin",
        "category": "Geral",
        "details": {
            "source_table": "50",
            "target_room": "10",
            "total": 77.0,
            "items": [
                {
                    "id": "item1",
                    "name": "Burger",
                    "qty": 1,
                    "price": 50.0,
                    "waiter": "Waiter A"
                },
                {
                    "id": "item2",
                    "name": "Coke",
                    "qty": 2,
                    "price": 10.0,
                    "waiter": "Waiter B"
                }
            ],
            "user": "Admin",
            "description": "Mesa 50 -> Quarto 10"
        }
    },
    {
        "id": "SYS_20260203164636153378",
        "timestamp": "03/02/2026 16:46:36",
        "timestamp_iso": "2026-02-03T16:46:36.153434",
        "action": "Cardápio Atualizado",
        "user": "Sistema",
        "category": "Cardápio",
        "details": {
            "id": "2",
            "name": "Acai",
            "category": "Sobremesas",
            "message": "Produto \"Acai\" atualizado."
        }
    },
    {
        "id": "SYS_20260203164647989596",
        "timestamp": "03/02/2026 16:46:47",
        "timestamp_iso": "2026-02-03T16:46:47.989637",
        "action": "Cardápio Atualizado",
        "user": "Sistema",
        "category": "Cardápio",
        "details": {
            "id": "2",
            "name": "Acai",
            "category": "Sobremesas",
            "message": "Produto \"Acai\" atualizado."
        }
    },
    {
        "id": "SYS_20260203164659558964",
        "timestamp": "03/02/2026 16:46:59",
        "timestamp_iso": "2026-02-03T16:46:59.560668",
        "action": "Cardápio Atualizado",
        "user": "Sistema",
        "category": "Cardápio",
        "details": {
            "id": "2",
            "name": "Acai",
            "category": "Sobremesas",
            "message": "Produto \"Acai\" atualizado."
        }
    },
    {
        "id": "SYS_20260203164740646238",
        "timestamp": "03/02/2026 16:47:40",
        "timestamp_iso": "2026-02-03T16:47:40.646252",
        "action": "close_cashier",
        "user": "test_user",
        "category": "Caixa",
        "details": {
            "session_id": "SESSION_123",
            "closing_balance": 100.0,
            "difference": 0.0,
            "opened_at": "01/01/2026 10:00",
            "closed_at": "03/02/2026 16:47",
            "department": "Recepção"
        }
    },
    {
        "id": "SYS_20260203164740869000",
        "timestamp": "03/02/2026 16:47:40",
        "timestamp_iso": "2026-02-03T16:47:40.869016",
        "action": "transfer_to_room",
        "user": "Admin",
        "category": "Geral",
        "details": {
            "source_table": "40",
            "target_room": "01",
            "total": 100.0,
            "items": [
                {
                    "name": "Item 1",
                    "price": 100.0,
                    "qty": 1,
                    "waiter": "Waiter1"
                }
            ],
            "user": "Admin",
            "description": "Mesa 40 -> Quarto 01"
        }
    },
    {
        "id": "SYS_20260203164740906468",
        "timestamp": "03/02/2026 16:47:40",
        "timestamp_iso": "2026-02-03T16:47:40.906483",
        "action": "transfer_to_room",
        "user": "Admin",
        "category": "Geral",
        "details": {
            "source_table": "41",
            "target_room": "01",
            "total": 110.0,
            "items": [
                {
                    "name": "Item 2",
                    "price": 100.0,
                    "qty": 1,
                    "waiter": "Waiter1"
                }
            ],
            "user": "Admin",
            "description": "Mesa 41 -> Quarto 01"
        }
    },
    {
        "id": "SYS_20260203164740938168",
        "timestamp": "03/02/2026 16:47:40",
        "timestamp_iso": "2026-02-03T16:47:40.938182",
        "action": "cancel_consumption",
        "user": "admin_user",
        "category": "Cancelamento",
        "details": {
            "charge_id": "CHARGE_TEST_001",
            "room_number": "101",
            "total": 100.0,
            "old_status": "pending",
            "justification": "Erro de lançamento"
        }
    },
    {
        "id": "SYS_20260203164741896493",
        "timestamp": "03/02/2026 16:47:41",
        "timestamp_iso": "2026-02-03T16:47:41.896513",
        "action": "transfer_to_room",
        "user": "admin",
        "category": "Geral",
        "details": {
            "source_table": "33",
            "target_room": "33",
            "total": 5.5,
            "items": [
                {
                    "id": "0e490857-a1ef-4b8a-8d67-643fbe94f57c",
                    "printed": false,
                    "print_status": "error",
                    "name": "Coca Cola",
                    "flavor": null,
                    "qty": 1.0,
                    "price": 5.0,
                    "complements": [],
                    "accompaniments": [],
                    "questions_answers": [],
                    "observations": [],
                    "category": "Bebidas",
                    "service_fee_exempt": false,
                    "source": "restaurant",
                    "waiter": "GarcomZ",
                    "created_at": "03/02/2026 16:47"
                }
            ],
            "user": "admin",
            "description": "Mesa 33 -> Quarto 33"
        }
    },
    {
        "id": "SYS_20260203164742720317",
        "timestamp": "03/02/2026 16:47:42",
        "timestamp_iso": "2026-02-03T16:47:42.720336",
        "action": "Login",
        "user": "admin",
        "category": "Autenticação",
        "details": "Usuário admin entrou no sistema"
    },
    {
        "id": "SYS_20260203164743210496",
        "timestamp": "03/02/2026 16:47:43",
        "timestamp_iso": "2026-02-03T16:47:43.210518",
        "action": "cancel_consumption",
        "user": "admin_user",
        "category": "Cancelamento",
        "details": {
            "charge_id": "TEST_CHARGE_20260203164743",
            "room_number": "999",
            "total": 10.0,
            "old_status": "pending",
            "justification": "Integration Test Justification"
        }
    },
    {
        "id": "SYS_20260203164743412236",
        "timestamp": "03/02/2026 16:47:43",
        "timestamp_iso": "2026-02-03T16:47:43.412255",
        "action": "Cardápio Criado",
        "user": "Sistema",
        "category": "Cardápio",
        "details": {
            "name": "Test Burger",
            "category": "Lanches",
            "message": "Produto \"Test Burger\" criado."
        }
    },
    {
        "id": "SYS_20260203164743855456",
        "timestamp": "03/02/2026 16:47:43",
        "timestamp_iso": "2026-02-03T16:47:43.855477",
        "action": "Cardápio Criado",
        "user": "Sistema",
        "category": "Cardápio",
        "details": {
            "name": "Bolo Especial",
            "category": "Sobremesas",
            "message": "Produto \"Bolo Especial\" criado."
        }
    },
    {
        "id": "SYS_20260203164743913452",
        "timestamp": "03/02/2026 16:47:43",
        "timestamp_iso": "2026-02-03T16:47:43.913468",
        "action": "Cardápio Atualizado",
        "user": "Sistema",
        "category": "Cardápio",
        "details": {
            "id": "1",
            "name": "Bolo Especial (Editado)",
            "category": "Sobremesas",
            "message": "Produto \"Bolo Especial (Editado)\" atualizado."
        }
    },
    {
        "id": "SYS_20260203164744276893",
        "timestamp": "03/02/2026 16:47:44",
        "timestamp_iso": "2026-02-03T16:47:44.276910",
        "action": "transfer_item",
        "user": "SupervisorUser",
        "category": "Restaurante",
        "details": {
            "description": "Transferiu 1.0x Coke da Mesa 10 para Mesa 20",
            "source_table": "10",
            "target_table": "20",
            "item": "Coke",
            "qty": 1.0,
            "user": "SupervisorUser"
        }
    },
    {
        "id": "SYS_20260203164744305501",
        "timestamp": "03/02/2026 16:47:44",
        "timestamp_iso": "2026-02-03T16:47:44.305524",
        "action": "transfer_item",
        "user": "SupervisorUser",
        "category": "Restaurante",
        "details": {
            "description": "Transferiu 1.0x Coke da Mesa 10 para Mesa 20",
            "source_table": "10",
            "target_table": "20",
            "item": "Coke",
            "qty": 1.0,
            "user": "SupervisorUser"
        }
    },
    {
        "id": "SYS_20260203164744340748",
        "timestamp": "03/02/2026 16:47:44",
        "timestamp_iso": "2026-02-03T16:47:44.340775",
        "action": "transfer_to_room",
        "user": "Admin",
        "category": "Geral",
        "details": {
            "source_table": "10",
            "target_room": "101",
            "total": 22.0,
            "items": [
                {
                    "name": "Burger",
                    "price": 20,
                    "qty": 1,
                    "source": "restaurant"
                }
            ],
            "user": "Admin",
            "description": "Mesa 10 -> Quarto 101"
        }
    },
    {
        "id": "SYS_20260203164744358108",
        "timestamp": "03/02/2026 16:47:44",
        "timestamp_iso": "2026-02-03T16:47:44.358130",
        "action": "transfer_to_room",
        "user": "Admin",
        "category": "Geral",
        "details": {
            "source_table": "10",
            "target_room": "101",
            "total": 22.0,
            "items": [
                {
                    "name": "Burger",
                    "price": 20,
                    "qty": 1,
                    "source": "restaurant"
                }
            ],
            "user": "Admin",
            "description": "Mesa 10 -> Quarto 101"
        }
    },
    {
        "id": "SYS_20260203164744379719",
        "timestamp": "03/02/2026 16:47:44",
        "timestamp_iso": "2026-02-03T16:47:44.379743",
        "action": "transfer_to_room",
        "user": "Admin",
        "category": "Geral",
        "details": {
            "source_table": "10",
            "target_room": "101",
            "total": 22.0,
            "items": [
                {
                    "name": "Burger",
                    "price": 20,
                    "qty": 1,
                    "source": "restaurant"
                }
            ],
            "user": "Admin",
            "description": "Mesa 10 -> Quarto 101"
        }
    },
    {
        "id": "SYS_20260203164744415431",
        "timestamp": "03/02/2026 16:47:44",
        "timestamp_iso": "2026-02-03T16:47:44.415450",
        "action": "transfer_to_room",
        "user": "Admin",
        "category": "Geral",
        "details": {
            "source_table": "50",
            "target_room": "10",
            "total": 77.0,
            "items": [
                {
                    "id": "item1",
                    "name": "Burger",
                    "qty": 1,
                    "price": 50.0,
                    "waiter": "Waiter A"
                },
                {
                    "id": "item2",
                    "name": "Coke",
                    "qty": 2,
                    "price": 10.0,
                    "waiter": "Waiter B"
                }
            ],
            "user": "Admin",
            "description": "Mesa 50 -> Quarto 10"
        }
    },
    {
        "id": "SYS_20260203165159330830",
        "timestamp": "03/02/2026 16:51:59",
        "timestamp_iso": "2026-02-03T16:51:59.330849",
        "action": "close_cashier",
        "user": "test_user",
        "category": "Caixa",
        "details": {
            "session_id": "SESSION_123",
            "closing_balance": 100.0,
            "difference": 0.0,
            "opened_at": "01/01/2026 10:00",
            "closed_at": "03/02/2026 16:51",
            "department": "Recepção"
        }
    },
    {
        "id": "SYS_20260203165159500898",
        "timestamp": "03/02/2026 16:51:59",
        "timestamp_iso": "2026-02-03T16:51:59.500919",
        "action": "transfer_to_room",
        "user": "Admin",
        "category": "Geral",
        "details": {
            "source_table": "40",
            "target_room": "01",
            "total": 100.0,
            "items": [
                {
                    "name": "Item 1",
                    "price": 100.0,
                    "qty": 1,
                    "waiter": "Waiter1"
                }
            ],
            "user": "Admin",
            "description": "Mesa 40 -> Quarto 01"
        }
    },
    {
        "id": "SYS_20260203165159536030",
        "timestamp": "03/02/2026 16:51:59",
        "timestamp_iso": "2026-02-03T16:51:59.536052",
        "action": "transfer_to_room",
        "user": "Admin",
        "category": "Geral",
        "details": {
            "source_table": "41",
            "target_room": "01",
            "total": 110.0,
            "items": [
                {
                    "name": "Item 2",
                    "price": 100.0,
                    "qty": 1,
                    "waiter": "Waiter1"
                }
            ],
            "user": "Admin",
            "description": "Mesa 41 -> Quarto 01"
        }
    },
    {
        "id": "SYS_20260203165159571474",
        "timestamp": "03/02/2026 16:51:59",
        "timestamp_iso": "2026-02-03T16:51:59.571489",
        "action": "cancel_consumption",
        "user": "admin_user",
        "category": "Cancelamento",
        "details": {
            "charge_id": "CHARGE_TEST_001",
            "room_number": "101",
            "total": 100.0,
            "old_status": "pending",
            "justification": "Erro de lançamento"
        }
    },
    {
        "id": "SYS_20260203165200407832",
        "timestamp": "03/02/2026 16:52:00",
        "timestamp_iso": "2026-02-03T16:52:00.407848",
        "action": "transfer_to_room",
        "user": "admin",
        "category": "Geral",
        "details": {
            "source_table": "33",
            "target_room": "33",
            "total": 5.5,
            "items": [
                {
                    "id": "9e0fc13e-5b3e-4d1f-9f94-1e31bfabc436",
                    "printed": false,
                    "print_status": "error",
                    "name": "Coca Cola",
                    "flavor": null,
                    "qty": 1.0,
                    "price": 5.0,
                    "complements": [],
                    "accompaniments": [],
                    "questions_answers": [],
                    "observations": [],
                    "category": "Bebidas",
                    "service_fee_exempt": false,
                    "source": "restaurant",
                    "waiter": "GarcomZ",
                    "created_at": "03/02/2026 16:52"
                }
            ],
            "user": "admin",
            "description": "Mesa 33 -> Quarto 33"
        }
    },
    {
        "id": "SYS_20260203165200899708",
        "timestamp": "03/02/2026 16:52:00",
        "timestamp_iso": "2026-02-03T16:52:00.899722",
        "action": "Login",
        "user": "admin",
        "category": "Autenticação",
        "details": "Usuário admin entrou no sistema"
    },
    {
        "id": "SYS_20260203165201300061",
        "timestamp": "03/02/2026 16:52:01",
        "timestamp_iso": "2026-02-03T16:52:01.300078",
        "action": "cancel_consumption",
        "user": "admin_user",
        "category": "Cancelamento",
        "details": {
            "charge_id": "TEST_CHARGE_20260203165201",
            "room_number": "999",
            "total": 10.0,
            "old_status": "pending",
            "justification": "Integration Test Justification"
        }
    },
    {
        "id": "SYS_20260203165201421215",
        "timestamp": "03/02/2026 16:52:01",
        "timestamp_iso": "2026-02-03T16:52:01.421231",
        "action": "Cardápio Criado",
        "user": "Sistema",
        "category": "Cardápio",
        "details": {
            "name": "Test Burger",
            "category": "Lanches",
            "message": "Produto \"Test Burger\" criado."
        }
    },
    {
        "id": "SYS_20260203165201793243",
        "timestamp": "03/02/2026 16:52:01",
        "timestamp_iso": "2026-02-03T16:52:01.793262",
        "action": "Cardápio Criado",
        "user": "Sistema",
        "category": "Cardápio",
        "details": {
            "name": "Bolo Especial",
            "category": "Sobremesas",
            "message": "Produto \"Bolo Especial\" criado."
        }
    },
    {
        "id": "SYS_20260203165201842436",
        "timestamp": "03/02/2026 16:52:01",
        "timestamp_iso": "2026-02-03T16:52:01.842452",
        "action": "Cardápio Atualizado",
        "user": "Sistema",
        "category": "Cardápio",
        "details": {
            "id": "1",
            "name": "Bolo Especial (Editado)",
            "category": "Sobremesas",
            "message": "Produto \"Bolo Especial (Editado)\" atualizado."
        }
    },
    {
        "id": "SYS_20260203165202113536",
        "timestamp": "03/02/2026 16:52:02",
        "timestamp_iso": "2026-02-03T16:52:02.113548",
        "action": "transfer_item",
        "user": "SupervisorUser",
        "category": "Restaurante",
        "details": {
            "description": "Transferiu 1.0x Coke da Mesa 10 para Mesa 20",
            "source_table": "10",
            "target_table": "20",
            "item": "Coke",
            "qty": 1.0,
            "user": "SupervisorUser"
        }
    },
    {
        "id": "SYS_20260203165202135919",
        "timestamp": "03/02/2026 16:52:02",
        "timestamp_iso": "2026-02-03T16:52:02.135941",
        "action": "transfer_item",
        "user": "SupervisorUser",
        "category": "Restaurante",
        "details": {
            "description": "Transferiu 1.0x Coke da Mesa 10 para Mesa 20",
            "source_table": "10",
            "target_table": "20",
            "item": "Coke",
            "qty": 1.0,
            "user": "SupervisorUser"
        }
    },
    {
        "id": "SYS_20260203165202179683",
        "timestamp": "03/02/2026 16:52:02",
        "timestamp_iso": "2026-02-03T16:52:02.179718",
        "action": "transfer_to_room",
        "user": "Admin",
        "category": "Geral",
        "details": {
            "source_table": "10",
            "target_room": "101",
            "total": 22.0,
            "items": [
                {
                    "name": "Burger",
                    "price": 20,
                    "qty": 1,
                    "source": "restaurant"
                }
            ],
            "user": "Admin",
            "description": "Mesa 10 -> Quarto 101"
        }
    },
    {
        "id": "SYS_20260203165202204179",
        "timestamp": "03/02/2026 16:52:02",
        "timestamp_iso": "2026-02-03T16:52:02.204198",
        "action": "transfer_to_room",
        "user": "Admin",
        "category": "Geral",
        "details": {
            "source_table": "10",
            "target_room": "101",
            "total": 22.0,
            "items": [
                {
                    "name": "Burger",
                    "price": 20,
                    "qty": 1,
                    "source": "restaurant"
                }
            ],
            "user": "Admin",
            "description": "Mesa 10 -> Quarto 101"
        }
    },
    {
        "id": "SYS_20260203165202237078",
        "timestamp": "03/02/2026 16:52:02",
        "timestamp_iso": "2026-02-03T16:52:02.237103",
        "action": "transfer_to_room",
        "user": "Admin",
        "category": "Geral",
        "details": {
            "source_table": "10",
            "target_room": "101",
            "total": 22.0,
            "items": [
                {
                    "name": "Burger",
                    "price": 20,
                    "qty": 1,
                    "source": "restaurant"
                }
            ],
            "user": "Admin",
            "description": "Mesa 10 -> Quarto 101"
        }
    },
    {
        "id": "SYS_20260203165202279080",
        "timestamp": "03/02/2026 16:52:02",
        "timestamp_iso": "2026-02-03T16:52:02.279110",
        "action": "transfer_to_room",
        "user": "Admin",
        "category": "Geral",
        "details": {
            "source_table": "50",
            "target_room": "10",
            "total": 77.0,
            "items": [
                {
                    "id": "item1",
                    "name": "Burger",
                    "qty": 1,
                    "price": 50.0,
                    "waiter": "Waiter A"
                },
                {
                    "id": "item2",
                    "name": "Coke",
                    "qty": 2,
                    "price": 10.0,
                    "waiter": "Waiter B"
                }
            ],
            "user": "Admin",
            "description": "Mesa 50 -> Quarto 10"
        }
    },
    {
        "id": "SYS_20260203171805663105",
        "timestamp": "03/02/2026 17:18:05",
        "timestamp_iso": "2026-02-03T17:18:05.663117",
        "action": "close_cashier",
        "user": "test_user",
        "category": "Caixa",
        "details": {
            "session_id": "SESSION_123",
            "closing_balance": 100.0,
            "difference": 0.0,
            "opened_at": "01/01/2026 10:00",
            "closed_at": "03/02/2026 17:18",
            "department": "Recepção"
        }
    },
    {
        "id": "SYS_20260203171805777736",
        "timestamp": "03/02/2026 17:18:05",
        "timestamp_iso": "2026-02-03T17:18:05.777751",
        "action": "cancel_consumption",
        "user": "admin_user",
        "category": "Cancelamento",
        "details": {
            "charge_id": "CHARGE_TEST_001",
            "room_number": "101",
            "total": 100.0,
            "old_status": "pending",
            "justification": "Erro de lançamento"
        }
    },
    {
        "id": "SYS_20260203171806251074",
        "timestamp": "03/02/2026 17:18:06",
        "timestamp_iso": "2026-02-03T17:18:06.251088",
        "action": "Login",
        "user": "admin",
        "category": "Autenticação",
        "details": "Usuário admin entrou no sistema"
    },
    {
        "id": "SYS_20260203171806718617",
        "timestamp": "03/02/2026 17:18:06",
        "timestamp_iso": "2026-02-03T17:18:06.718634",
        "action": "cancel_consumption",
        "user": "admin_user",
        "category": "Cancelamento",
        "details": {
            "charge_id": "TEST_CHARGE_20260203171806",
            "room_number": "999",
            "total": 10.0,
            "old_status": "pending",
            "justification": "Integration Test Justification"
        }
    },
    {
        "id": "SYS_20260203171806861092",
        "timestamp": "03/02/2026 17:18:06",
        "timestamp_iso": "2026-02-03T17:18:06.861107",
        "action": "Cardápio Criado",
        "user": "Sistema",
        "category": "Cardápio",
        "details": {
            "name": "Test Burger",
            "category": "Lanches",
            "message": "Produto \"Test Burger\" criado."
        }
    },
    {
        "id": "SYS_20260203171807344201",
        "timestamp": "03/02/2026 17:18:07",
        "timestamp_iso": "2026-02-03T17:18:07.344213",
        "action": "transfer_item",
        "user": "SupervisorUser",
        "category": "Restaurante",
        "details": {
            "description": "Transferiu 1.0x Coke da Mesa 10 para Mesa 20",
            "source_table": "10",
            "target_table": "20",
            "item": "Coke",
            "qty": 1.0,
            "user": "SupervisorUser"
        }
    },
    {
        "id": "SYS_20260203171807357853",
        "timestamp": "03/02/2026 17:18:07",
        "timestamp_iso": "2026-02-03T17:18:07.357864",
        "action": "transfer_item",
        "user": "SupervisorUser",
        "category": "Restaurante",
        "details": {
            "description": "Transferiu 1.0x Coke da Mesa 10 para Mesa 20",
            "source_table": "10",
            "target_table": "20",
            "item": "Coke",
            "qty": 1.0,
            "user": "SupervisorUser"
        }
    },
    {
        "id": "SYS_20260203171807374532",
        "timestamp": "03/02/2026 17:18:07",
        "timestamp_iso": "2026-02-03T17:18:07.374546",
        "action": "transfer_to_room",
        "user": "Admin",
        "category": "Geral",
        "details": {
            "source_table": "10",
            "target_room": "101",
            "total": 22.0,
            "items": [
                {
                    "name": "Burger",
                    "price": 20,
                    "qty": 1,
                    "source": "restaurant"
                }
            ],
            "user": "Admin",
            "description": "Mesa 10 -> Quarto 101"
        }
    },
    {
        "id": "SYS_20260203171807387101",
        "timestamp": "03/02/2026 17:18:07",
        "timestamp_iso": "2026-02-03T17:18:07.387115",
        "action": "transfer_to_room",
        "user": "Admin",
        "category": "Geral",
        "details": {
            "source_table": "10",
            "target_room": "101",
            "total": 22.0,
            "items": [
                {
                    "name": "Burger",
                    "price": 20,
                    "qty": 1,
                    "source": "restaurant"
                }
            ],
            "user": "Admin",
            "description": "Mesa 10 -> Quarto 101"
        }
    },
    {
        "id": "SYS_20260203171807401276",
        "timestamp": "03/02/2026 17:18:07",
        "timestamp_iso": "2026-02-03T17:18:07.401292",
        "action": "transfer_to_room",
        "user": "Admin",
        "category": "Geral",
        "details": {
            "source_table": "10",
            "target_room": "101",
            "total": 22.0,
            "items": [
                {
                    "name": "Burger",
                    "price": 20,
                    "qty": 1,
                    "source": "restaurant"
                }
            ],
            "user": "Admin",
            "description": "Mesa 10 -> Quarto 101"
        }
    },
    {
        "id": "SYS_20260203174413015592",
        "timestamp": "03/02/2026 17:44:13",
        "timestamp_iso": "2026-02-03T17:44:13.015610",
        "action": "close_cashier",
        "user": "test_user",
        "category": "Caixa",
        "details": {
            "session_id": "SESSION_123",
            "closing_balance": 100.0,
            "difference": 0.0,
            "opened_at": "01/01/2026 10:00",
            "closed_at": "03/02/2026 17:44",
            "department": "Recepção"
        }
    },
    {
        "id": "SYS_20260203174413170397",
        "timestamp": "03/02/2026 17:44:13",
        "timestamp_iso": "2026-02-03T17:44:13.170423",
        "action": "cancel_consumption",
        "user": "admin_user",
        "category": "Cancelamento",
        "details": {
            "charge_id": "CHARGE_TEST_001",
            "room_number": "101",
            "total": 100.0,
            "old_status": "pending",
            "justification": "Erro de lançamento"
        }
    },
    {
        "id": "SYS_20260203174413713520",
        "timestamp": "03/02/2026 17:44:13",
        "timestamp_iso": "2026-02-03T17:44:13.713538",
        "action": "Login",
        "user": "admin",
        "category": "Autenticação",
        "details": "Usuário admin entrou no sistema"
    },
    {
        "id": "SYS_20260203174414369982",
        "timestamp": "03/02/2026 17:44:14",
        "timestamp_iso": "2026-02-03T17:44:14.370008",
        "action": "cancel_consumption",
        "user": "admin_user",
        "category": "Cancelamento",
        "details": {
            "charge_id": "TEST_CHARGE_20260203174414",
            "room_number": "999",
            "total": 10.0,
            "old_status": "pending",
            "justification": "Integration Test Justification"
        }
    },
    {
        "id": "SYS_20260203174414567908",
        "timestamp": "03/02/2026 17:44:14",
        "timestamp_iso": "2026-02-03T17:44:14.567928",
        "action": "Cardápio Criado",
        "user": "Sistema",
        "category": "Cardápio",
        "details": {
            "name": "Test Burger",
            "category": "Lanches",
            "message": "Produto \"Test Burger\" criado."
        }
    },
    {
        "id": "SYS_20260203174415197424",
        "timestamp": "03/02/2026 17:44:15",
        "timestamp_iso": "2026-02-03T17:44:15.197439",
        "action": "transfer_item",
        "user": "SupervisorUser",
        "category": "Restaurante",
        "details": {
            "description": "Transferiu 1.0x Coke da Mesa 10 para Mesa 20",
            "source_table": "10",
            "target_table": "20",
            "item": "Coke",
            "qty": 1.0,
            "user": "SupervisorUser"
        }
    },
    {
        "id": "SYS_20260203174415217851",
        "timestamp": "03/02/2026 17:44:15",
        "timestamp_iso": "2026-02-03T17:44:15.217890",
        "action": "transfer_item",
        "user": "SupervisorUser",
        "category": "Restaurante",
        "details": {
            "description": "Transferiu 1.0x Coke da Mesa 10 para Mesa 20",
            "source_table": "10",
            "target_table": "20",
            "item": "Coke",
            "qty": 1.0,
            "user": "SupervisorUser"
        }
    },
    {
        "id": "SYS_20260203174415244048",
        "timestamp": "03/02/2026 17:44:15",
        "timestamp_iso": "2026-02-03T17:44:15.244065",
        "action": "transfer_to_room",
        "user": "Admin",
        "category": "Geral",
        "details": {
            "source_table": "10",
            "target_room": "101",
            "total": 22.0,
            "items": [
                {
                    "name": "Burger",
                    "price": 20,
                    "qty": 1,
                    "source": "restaurant"
                }
            ],
            "user": "Admin",
            "description": "Mesa 10 -> Quarto 101"
        }
    },
    {
        "id": "SYS_20260203174415265594",
        "timestamp": "03/02/2026 17:44:15",
        "timestamp_iso": "2026-02-03T17:44:15.265619",
        "action": "transfer_to_room",
        "user": "Admin",
        "category": "Geral",
        "details": {
            "source_table": "10",
            "target_room": "101",
            "total": 22.0,
            "items": [
                {
                    "name": "Burger",
                    "price": 20,
                    "qty": 1,
                    "source": "restaurant"
                }
            ],
            "user": "Admin",
            "description": "Mesa 10 -> Quarto 101"
        }
    },
    {
        "id": "SYS_20260203174415288232",
        "timestamp": "03/02/2026 17:44:15",
        "timestamp_iso": "2026-02-03T17:44:15.288250",
        "action": "transfer_to_room",
        "user": "Admin",
        "category": "Geral",
        "details": {
            "source_table": "10",
            "target_room": "101",
            "total": 22.0,
            "items": [
                {
                    "name": "Burger",
                    "price": 20,
                    "qty": 1,
                    "source": "restaurant"
                }
            ],
            "user": "Admin",
            "description": "Mesa 10 -> Quarto 101"
        }
    },
    {
        "id": "SYS_20260203180213027443",
        "timestamp": "03/02/2026 18:02:13",
        "timestamp_iso": "2026-02-03T18:02:13.027457",
        "action": "close_cashier",
        "user": "test_user",
        "category": "Caixa",
        "details": {
            "session_id": "SESSION_123",
            "closing_balance": 100.0,
            "difference": 0.0,
            "opened_at": "01/01/2026 10:00",
            "closed_at": "03/02/2026 18:02",
            "department": "Recepção"
        }
    },
    {
        "id": "SYS_20260203180213164391",
        "timestamp": "03/02/2026 18:02:13",
        "timestamp_iso": "2026-02-03T18:02:13.164406",
        "action": "cancel_consumption",
        "user": "admin_user",
        "category": "Cancelamento",
        "details": {
            "charge_id": "CHARGE_TEST_001",
            "room_number": "101",
            "total": 100.0,
            "old_status": "pending",
            "justification": "Erro de lançamento"
        }
    },
    {
        "id": "SYS_20260203180213774168",
        "timestamp": "03/02/2026 18:02:13",
        "timestamp_iso": "2026-02-03T18:02:13.774182",
        "action": "Login",
        "user": "admin",
        "category": "Autenticação",
        "details": "Usuário admin entrou no sistema"
    },
    {
        "id": "SYS_20260203180214265072",
        "timestamp": "03/02/2026 18:02:14",
        "timestamp_iso": "2026-02-03T18:02:14.265090",
        "action": "cancel_consumption",
        "user": "admin_user",
        "category": "Cancelamento",
        "details": {
            "charge_id": "TEST_CHARGE_20260203180214",
            "room_number": "999",
            "total": 10.0,
            "old_status": "pending",
            "justification": "Integration Test Justification"
        }
    },
    {
        "id": "SYS_20260203180214388686",
        "timestamp": "03/02/2026 18:02:14",
        "timestamp_iso": "2026-02-03T18:02:14.388702",
        "action": "Cardápio Criado",
        "user": "Sistema",
        "category": "Cardápio",
        "details": {
            "name": "Test Burger",
            "category": "Lanches",
            "message": "Produto \"Test Burger\" criado."
        }
    },
    {
        "id": "SYS_20260203180214999956",
        "timestamp": "03/02/2026 18:02:14",
        "timestamp_iso": "2026-02-03T18:02:14.999971",
        "action": "transfer_item",
        "user": "SupervisorUser",
        "category": "Restaurante",
        "details": {
            "description": "Transferiu 1.0x Coke da Mesa 10 para Mesa 20",
            "source_table": "10",
            "target_table": "20",
            "item": "Coke",
            "qty": 1.0,
            "user": "SupervisorUser"
        }
    },
    {
        "id": "SYS_20260203180215016111",
        "timestamp": "03/02/2026 18:02:15",
        "timestamp_iso": "2026-02-03T18:02:15.016123",
        "action": "transfer_item",
        "user": "SupervisorUser",
        "category": "Restaurante",
        "details": {
            "description": "Transferiu 1.0x Coke da Mesa 10 para Mesa 20",
            "source_table": "10",
            "target_table": "20",
            "item": "Coke",
            "qty": 1.0,
            "user": "SupervisorUser"
        }
    },
    {
        "id": "SYS_20260203180215036355",
        "timestamp": "03/02/2026 18:02:15",
        "timestamp_iso": "2026-02-03T18:02:15.036371",
        "action": "transfer_to_room",
        "user": "Admin",
        "category": "Geral",
        "details": {
            "source_table": "10",
            "target_room": "101",
            "total": 22.0,
            "items": [
                {
                    "name": "Burger",
                    "price": 20,
                    "qty": 1,
                    "source": "restaurant"
                }
            ],
            "user": "Admin",
            "description": "Mesa 10 -> Quarto 101"
        }
    },
    {
        "id": "SYS_20260203180215051614",
        "timestamp": "03/02/2026 18:02:15",
        "timestamp_iso": "2026-02-03T18:02:15.051629",
        "action": "transfer_to_room",
        "user": "Admin",
        "category": "Geral",
        "details": {
            "source_table": "10",
            "target_room": "101",
            "total": 22.0,
            "items": [
                {
                    "name": "Burger",
                    "price": 20,
                    "qty": 1,
                    "source": "restaurant"
                }
            ],
            "user": "Admin",
            "description": "Mesa 10 -> Quarto 101"
        }
    },
    {
        "id": "SYS_20260203180215068991",
        "timestamp": "03/02/2026 18:02:15",
        "timestamp_iso": "2026-02-03T18:02:15.069006",
        "action": "transfer_to_room",
        "user": "Admin",
        "category": "Geral",
        "details": {
            "source_table": "10",
            "target_room": "101",
            "total": 22.0,
            "items": [
                {
                    "name": "Burger",
                    "price": 20,
                    "qty": 1,
                    "source": "restaurant"
                }
            ],
            "user": "Admin",
            "description": "Mesa 10 -> Quarto 101"
        }
    },
    {
        "id": "SYS_20260203181801379699",
        "timestamp": "03/02/2026 18:18:01",
        "timestamp_iso": "2026-02-03T18:18:01.379711",
        "action": "close_cashier",
        "user": "test_user",
        "category": "Caixa",
        "details": {
            "session_id": "SESSION_123",
            "closing_balance": 100.0,
            "difference": 0.0,
            "opened_at": "01/01/2026 10:00",
            "closed_at": "03/02/2026 18:18",
            "department": "Recepção"
        }
    },
    {
        "id": "SYS_20260203181801487413",
        "timestamp": "03/02/2026 18:18:01",
        "timestamp_iso": "2026-02-03T18:18:01.487426",
        "action": "cancel_consumption",
        "user": "admin_user",
        "category": "Cancelamento",
        "details": {
            "charge_id": "CHARGE_TEST_001",
            "room_number": "101",
            "total": 100.0,
            "old_status": "pending",
            "justification": "Erro de lançamento"
        }
    },
    {
        "id": "SYS_20260203181801947681",
        "timestamp": "03/02/2026 18:18:01",
        "timestamp_iso": "2026-02-03T18:18:01.947693",
        "action": "Login",
        "user": "admin",
        "category": "Autenticação",
        "details": "Usuário admin entrou no sistema"
    },
    {
        "id": "SYS_20260203181802351428",
        "timestamp": "03/02/2026 18:18:02",
        "timestamp_iso": "2026-02-03T18:18:02.351443",
        "action": "cancel_consumption",
        "user": "admin_user",
        "category": "Cancelamento",
        "details": {
            "charge_id": "TEST_CHARGE_20260203181802",
            "room_number": "999",
            "total": 10.0,
            "old_status": "pending",
            "justification": "Integration Test Justification"
        }
    },
    {
        "id": "SYS_20260203181802456194",
        "timestamp": "03/02/2026 18:18:02",
        "timestamp_iso": "2026-02-03T18:18:02.456207",
        "action": "Cardápio Criado",
        "user": "Sistema",
        "category": "Cardápio",
        "details": {
            "name": "Test Burger",
            "category": "Lanches",
            "message": "Produto \"Test Burger\" criado."
        }
    },
    {
        "id": "SYS_20260203181802908395",
        "timestamp": "03/02/2026 18:18:02",
        "timestamp_iso": "2026-02-03T18:18:02.908409",
        "action": "transfer_item",
        "user": "SupervisorUser",
        "category": "Restaurante",
        "details": {
            "description": "Transferiu 1.0x Coke da Mesa 10 para Mesa 20",
            "source_table": "10",
            "target_table": "20",
            "item": "Coke",
            "qty": 1.0,
            "user": "SupervisorUser"
        }
    },
    {
        "id": "SYS_20260203181802921844",
        "timestamp": "03/02/2026 18:18:02",
        "timestamp_iso": "2026-02-03T18:18:02.921855",
        "action": "transfer_item",
        "user": "SupervisorUser",
        "category": "Restaurante",
        "details": {
            "description": "Transferiu 1.0x Coke da Mesa 10 para Mesa 20",
            "source_table": "10",
            "target_table": "20",
            "item": "Coke",
            "qty": 1.0,
            "user": "SupervisorUser"
        }
    },
    {
        "id": "SYS_20260203181802939784",
        "timestamp": "03/02/2026 18:18:02",
        "timestamp_iso": "2026-02-03T18:18:02.939798",
        "action": "transfer_to_room",
        "user": "Admin",
        "category": "Geral",
        "details": {
            "source_table": "10",
            "target_room": "101",
            "total": 22.0,
            "items": [
                {
                    "name": "Burger",
                    "price": 20,
                    "qty": 1,
                    "source": "restaurant"
                }
            ],
            "user": "Admin",
            "description": "Mesa 10 -> Quarto 101"
        }
    },
    {
        "id": "SYS_20260203181802952695",
        "timestamp": "03/02/2026 18:18:02",
        "timestamp_iso": "2026-02-03T18:18:02.952709",
        "action": "transfer_to_room",
        "user": "Admin",
        "category": "Geral",
        "details": {
            "source_table": "10",
            "target_room": "101",
            "total": 22.0,
            "items": [
                {
                    "name": "Burger",
                    "price": 20,
                    "qty": 1,
                    "source": "restaurant"
                }
            ],
            "user": "Admin",
            "description": "Mesa 10 -> Quarto 101"
        }
    },
    {
        "id": "SYS_20260203181802966858",
        "timestamp": "03/02/2026 18:18:02",
        "timestamp_iso": "2026-02-03T18:18:02.966871",
        "action": "transfer_to_room",
        "user": "Admin",
        "category": "Geral",
        "details": {
            "source_table": "10",
            "target_room": "101",
            "total": 22.0,
            "items": [
                {
                    "name": "Burger",
                    "price": 20,
                    "qty": 1,
                    "source": "restaurant"
                }
            ],
            "user": "Admin",
            "description": "Mesa 10 -> Quarto 101"
        }
    },
    {
        "id": "SYS_20260203184552656577",
        "timestamp": "03/02/2026 18:45:52",
        "timestamp_iso": "2026-02-03T18:45:52.656593",
        "action": "close_cashier",
        "user": "test_user",
        "category": "Caixa",
        "details": {
            "session_id": "SESSION_123",
            "closing_balance": 100.0,
            "difference": 0.0,
            "opened_at": "01/01/2026 10:00",
            "closed_at": "03/02/2026 18:45",
            "department": "Recepção"
        }
    },
    {
        "id": "SYS_20260203184552781696",
        "timestamp": "03/02/2026 18:45:52",
        "timestamp_iso": "2026-02-03T18:45:52.781712",
        "action": "cancel_consumption",
        "user": "admin_user",
        "category": "Cancelamento",
        "details": {
            "charge_id": "CHARGE_TEST_001",
            "room_number": "101",
            "total": 100.0,
            "old_status": "pending",
            "justification": "Erro de lançamento"
        }
    },
    {
        "id": "SYS_20260203184553272735",
        "timestamp": "03/02/2026 18:45:53",
        "timestamp_iso": "2026-02-03T18:45:53.272749",
        "action": "Login",
        "user": "admin",
        "category": "Autenticação",
        "details": "Usuário admin entrou no sistema"
    },
    {
        "id": "SYS_20260203184553720454",
        "timestamp": "03/02/2026 18:45:53",
        "timestamp_iso": "2026-02-03T18:45:53.720471",
        "action": "cancel_consumption",
        "user": "admin_user",
        "category": "Cancelamento",
        "details": {
            "charge_id": "TEST_CHARGE_20260203184553",
            "room_number": "999",
            "total": 10.0,
            "old_status": "pending",
            "justification": "Integration Test Justification"
        }
    },
    {
        "id": "SYS_20260203184553855292",
        "timestamp": "03/02/2026 18:45:53",
        "timestamp_iso": "2026-02-03T18:45:53.855308",
        "action": "Cardápio Criado",
        "user": "Sistema",
        "category": "Cardápio",
        "details": {
            "name": "Test Burger",
            "category": "Lanches",
            "message": "Produto \"Test Burger\" criado."
        }
    },
    {
        "id": "SYS_20260203184554449128",
        "timestamp": "03/02/2026 18:45:54",
        "timestamp_iso": "2026-02-03T18:45:54.449141",
        "action": "transfer_item",
        "user": "SupervisorUser",
        "category": "Restaurante",
        "details": {
            "description": "Transferiu 1.0x Coke da Mesa 10 para Mesa 20",
            "source_table": "10",
            "target_table": "20",
            "item": "Coke",
            "qty": 1.0,
            "user": "SupervisorUser"
        }
    },
    {
        "id": "SYS_20260203184554466892",
        "timestamp": "03/02/2026 18:45:54",
        "timestamp_iso": "2026-02-03T18:45:54.466903",
        "action": "transfer_item",
        "user": "SupervisorUser",
        "category": "Restaurante",
        "details": {
            "description": "Transferiu 1.0x Coke da Mesa 10 para Mesa 20",
            "source_table": "10",
            "target_table": "20",
            "item": "Coke",
            "qty": 1.0,
            "user": "SupervisorUser"
        }
    },
    {
        "id": "SYS_20260203184554489406",
        "timestamp": "03/02/2026 18:45:54",
        "timestamp_iso": "2026-02-03T18:45:54.489423",
        "action": "transfer_to_room",
        "user": "Admin",
        "category": "Geral",
        "details": {
            "source_table": "10",
            "target_room": "101",
            "total": 22.0,
            "items": [
                {
                    "name": "Burger",
                    "price": 20,
                    "qty": 1,
                    "source": "restaurant"
                }
            ],
            "user": "Admin",
            "description": "Mesa 10 -> Quarto 101"
        }
    },
    {
        "id": "SYS_20260203184554504295",
        "timestamp": "03/02/2026 18:45:54",
        "timestamp_iso": "2026-02-03T18:45:54.504310",
        "action": "transfer_to_room",
        "user": "Admin",
        "category": "Geral",
        "details": {
            "source_table": "10",
            "target_room": "101",
            "total": 22.0,
            "items": [
                {
                    "name": "Burger",
                    "price": 20,
                    "qty": 1,
                    "source": "restaurant"
                }
            ],
            "user": "Admin",
            "description": "Mesa 10 -> Quarto 101"
        }
    },
    {
        "id": "SYS_20260203184554522079",
        "timestamp": "03/02/2026 18:45:54",
        "timestamp_iso": "2026-02-03T18:45:54.522093",
        "action": "transfer_to_room",
        "user": "Admin",
        "category": "Geral",
        "details": {
            "source_table": "10",
            "target_room": "101",
            "total": 22.0,
            "items": [
                {
                    "name": "Burger",
                    "price": 20,
                    "qty": 1,
                    "source": "restaurant"
                }
            ],
            "user": "Admin",
            "description": "Mesa 10 -> Quarto 101"
        }
    }
]